LICENSE
irc_bot/__init__.py
irc_bot/command_scheduler.py
irc_bot/irc_message.py
irc_bot/numeric_replies.py
irc_bot/rfc2812.txt
irc_bot/simple_irc_bot.py
irc_bot/utils.py
irc_bot-1.0.41.dist-info/METADATA
irc_bot-1.0.41.dist-info/WHEEL
irc_bot-1.0.41.dist-info/LICENSE
irc_bot-1.0.41.dist-info/RECORD
